datup/__init__.py
datup/core/__init__.py
datup/core/api.py
datup/core/credentials.py
datup/core/datup.py
datup/core/logger.py
datup/io/DatabasesIO.py
datup/io/__init__.py
datup/io/api.py
datup/io/dataio.py
datup/preparation/__init__.py
datup/preparation/api.py
datup/preparation/data_preparation.py
datup/timeseries/ExponentialSmoothing.py
datup/timeseries/RandomForestDelayEmbbeded.py
datup/timeseries/__init__.py
datup/timeseries/api.py
datup/timeseries/timeseries_errors.py
datup/timeseries/utils.py
datup/utils/__init__.py
datup/utils/api.py
datup/utils/utils.py
datup-0.1.8.post20.dist-info/LICENSE
datup-0.1.8.post20.dist-info/METADATA
datup-0.1.8.post20.dist-info/WHEEL
datup-0.1.8.post20.dist-info/top_level.txt
datup-0.1.8.post20.dist-info/RECORD
