Metadata-Version: 2.1
Name: datup
Version: 0.1.8-20
Summary: The version of this library and document is V 0.1.8_20
Home-page: https://datup.ai
Author: DatupDevOps
Author-email: devops@datup.ai
License: UNKNOWN
Platform: UNKNOWN
Classifier: Programming Language :: Python :: 3
Classifier: License :: OSI Approved :: MIT License
Classifier: Operating System :: OS Independent
Requires-Python: >=3.6
Requires-Dist: boto3
Requires-Dist: statsmodels (==0.11.0)
Requires-Dist: s3fs
Requires-Dist: scipy
Requires-Dist: sqlalchemy
Requires-Dist: pymysql
